{"test":[
{"name":"t1","dur":"309","m":"[]","r":"[r1]","fam":"fam1","prio":"1"},
{"name":"t2","dur":"737","m":"[]","r":"[]","fam":"fam1","prio":"1"},
{"name":"t3","dur":"759","m":"[]","r":"[r1, r3, r2]","fam":"fam1","prio":"1"},
{"name":"t4","dur":"181","m":"[]","r":"[]","fam":"fam1","prio":"1"},
{"name":"t5","dur":"462","m":"[]","r":"[]","fam":"fam1","prio":"1"},
{"name":"t6","dur":"8","m":"[]","r":"[]","fam":"fam1","prio":"1"},
{"name":"t7","dur":"780","m":"[]","r":"[]","fam":"fam1","prio":"1"},
{"name":"t8","dur":"718","m":"[]","r":"[]","fam":"fam1","prio":"1"},
{"name":"t9","dur":"245","m":"[]","r":"[]","fam":"fam1","prio":"1"},
{"name":"t10","dur":"742","m":"[m11, m16, m2, m17, m7, m5, m14]","r":"[]","fam":"fam1","prio":"1"},
{"name":"t11","dur":"641","m":"[]","r":"[]","fam":"fam1","prio":"1"},
{"name":"t12","dur":"756","m":"[]","r":"[]","fam":"fam1","prio":"1"},
{"name":"t13","dur":"536","m":"[]","r":"[r2, r1, r3]","fam":"fam1","prio":"1"},
{"name":"t14","dur":"649","m":"[]","r":"[]","fam":"fam1","prio":"1"},
{"name":"t15","dur":"578","m":"[]","r":"[]","fam":"fam1","prio":"1"},
{"name":"t16","dur":"492","m":"[]","r":"[]","fam":"fam1","prio":"1"},
{"name":"t17","dur":"624","m":"[m11]","r":"[r3, r1]","fam":"fam1","prio":"1"},
{"name":"t18","dur":"72","m":"[]","r":"[]","fam":"fam1","prio":"1"},
{"name":"t19","dur":"37","m":"[m12, m13, m17]","r":"[]","fam":"fam1","prio":"1"},
{"name":"t20","dur":"127","m":"[]","r":"[]","fam":"fam1","prio":"1"},
{"name":"t21","dur":"745","m":"[]","r":"[]","fam":"fam1","prio":"1"},
{"name":"t22","dur":"241","m":"[]","r":"[r2, r1]","fam":"fam1","prio":"1"},
{"name":"t23","dur":"144","m":"[m18, m9, m15, m13, m14]","r":"[]","fam":"fam1","prio":"1"},
{"name":"t24","dur":"63","m":"[]","r":"[]","fam":"fam1","prio":"1"},
{"name":"t25","dur":"398","m":"[]","r":"[]","fam":"fam1","prio":"1"},
{"name":"t26","dur":"390","m":"[]","r":"[r1]","fam":"fam1","prio":"1"},
{"name":"t27","dur":"578","m":"[m5, m19]","r":"[r2]","fam":"fam1","prio":"1"},
{"name":"t28","dur":"639","m":"[]","r":"[r3, r2, r1]","fam":"fam1","prio":"1"},
{"name":"t29","dur":"159","m":"[]","r":"[r1, r3]","fam":"fam1","prio":"1"},
{"name":"t30","dur":"702","m":"[]","r":"[r2, r1]","fam":"fam1","prio":"1"},
{"name":"t31","dur":"17","m":"[]","r":"[]","fam":"fam1","prio":"1"},
{"name":"t32","dur":"676","m":"[]","r":"[]","fam":"fam1","prio":"1"},
{"name":"t33","dur":"609","m":"[]","r":"[r1, r3]","fam":"fam1","prio":"1"},
{"name":"t34","dur":"485","m":"[]","r":"[]","fam":"fam1","prio":"1"},
{"name":"t35","dur":"88","m":"[]","r":"[r2, r1]","fam":"fam1","prio":"1"},
{"name":"t36","dur":"551","m":"[]","r":"[]","fam":"fam1","prio":"1"},
{"name":"t37","dur":"582","m":"[]","r":"[]","fam":"fam1","prio":"1"},
{"name":"t38","dur":"682","m":"[]","r":"[r2]","fam":"fam1","prio":"1"},
{"name":"t39","dur":"347","m":"[]","r":"[]","fam":"fam1","prio":"1"},
{"name":"t40","dur":"740","m":"[]","r":"[]","fam":"fam1","prio":"1"},
{"name":"t41","dur":"236","m":"[]","r":"[]","fam":"fam1","prio":"1"},
{"name":"t42","dur":"554","m":"[]","r":"[]","fam":"fam1","prio":"1"},
{"name":"t43","dur":"61","m":"[]","r":"[r3, r2, r1]","fam":"fam1","prio":"1"},
{"name":"t44","dur":"445","m":"[]","r":"[]","fam":"fam1","prio":"1"},
{"name":"t45","dur":"159","m":"[]","r":"[]","fam":"fam1","prio":"1"},
{"name":"t46","dur":"590","m":"[]","r":"[]","fam":"fam1","prio":"1"},
{"name":"t47","dur":"136","m":"[]","r":"[]","fam":"fam1","prio":"1"},
{"name":"t48","dur":"402","m":"[]","r":"[r3, r2, r1]","fam":"fam1","prio":"1"},
{"name":"t49","dur":"85","m":"[]","r":"[r2, r1]","fam":"fam1","prio":"1"},
{"name":"t50","dur":"60","m":"[]","r":"[r3]","fam":"fam1","prio":"1"},
{"name":"t51","dur":"146","m":"[]","r":"[]","fam":"fam1","prio":"1"},
{"name":"t52","dur":"421","m":"[]","r":"[]","fam":"fam1","prio":"1"},
{"name":"t53","dur":"680","m":"[m13, m7, m6, m18, m5, m4, m8, m19]","r":"[]","fam":"fam1","prio":"1"},
{"name":"t54","dur":"423","m":"[]","r":"[r2, r1, r3]","fam":"fam1","prio":"1"},
{"name":"t55","dur":"25","m":"[m11, m2]","r":"[]","fam":"fam1","prio":"1"},
{"name":"t56","dur":"352","m":"[]","r":"[]","fam":"fam1","prio":"1"},
{"name":"t57","dur":"565","m":"[]","r":"[r2]","fam":"fam1","prio":"1"},
{"name":"t58","dur":"348","m":"[m2, m12, m11]","r":"[]","fam":"fam1","prio":"1"},
{"name":"t59","dur":"654","m":"[]","r":"[r3]","fam":"fam1","prio":"1"},
{"name":"t60","dur":"298","m":"[m3, m13, m1, m6, m19, m16]","r":"[]","fam":"fam1","prio":"1"},
{"name":"t61","dur":"39","m":"[m7, m20, m15, m4]","r":"[]","fam":"fam1","prio":"1"},
{"name":"t62","dur":"199","m":"[]","r":"[r2, r3, r1]","fam":"fam1","prio":"1"},
{"name":"t63","dur":"751","m":"[]","r":"[]","fam":"fam1","prio":"1"},
{"name":"t64","dur":"303","m":"[m1, m17]","r":"[r1, r2]","fam":"fam1","prio":"1"},
{"name":"t65","dur":"431","m":"[]","r":"[]","fam":"fam1","prio":"1"},
{"name":"t66","dur":"260","m":"[]","r":"[]","fam":"fam1","prio":"1"},
{"name":"t67","dur":"26","m":"[]","r":"[]","fam":"fam1","prio":"1"},
{"name":"t68","dur":"789","m":"[]","r":"[]","fam":"fam1","prio":"1"},
{"name":"t69","dur":"495","m":"[m9, m2, m1, m7]","r":"[]","fam":"fam1","prio":"1"},
{"name":"t70","dur":"56","m":"[]","r":"[]","fam":"fam1","prio":"1"},
{"name":"t71","dur":"293","m":"[m5, m1, m4, m9, m8, m15]","r":"[]","fam":"fam1","prio":"1"},
{"name":"t72","dur":"83","m":"[]","r":"[]","fam":"fam1","prio":"1"},
{"name":"t73","dur":"636","m":"[]","r":"[r3, r2, r1]","fam":"fam1","prio":"1"},
{"name":"t74","dur":"618","m":"[]","r":"[]","fam":"fam1","prio":"1"},
{"name":"t75","dur":"488","m":"[m16, m6, m5]","r":"[]","fam":"fam1","prio":"1"},
{"name":"t76","dur":"430","m":"[]","r":"[]","fam":"fam1","prio":"1"},
{"name":"t77","dur":"86","m":"[]","r":"[]","fam":"fam1","prio":"1"},
{"name":"t78","dur":"29","m":"[]","r":"[]","fam":"fam1","prio":"1"},
{"name":"t79","dur":"246","m":"[]","r":"[]","fam":"fam1","prio":"1"},
{"name":"t80","dur":"761","m":"[]","r":"[]","fam":"fam1","prio":"1"},
{"name":"t81","dur":"420","m":"[m17]","r":"[]","fam":"fam1","prio":"1"},
{"name":"t82","dur":"468","m":"[]","r":"[r1]","fam":"fam1","prio":"1"},
{"name":"t83","dur":"414","m":"[]","r":"[]","fam":"fam1","prio":"1"},
{"name":"t84","dur":"24","m":"[]","r":"[]","fam":"fam1","prio":"1"},
{"name":"t85","dur":"784","m":"[]","r":"[]","fam":"fam1","prio":"1"},
{"name":"t86","dur":"100","m":"[]","r":"[r2, r3, r1]","fam":"fam1","prio":"1"},
{"name":"t87","dur":"201","m":"[m17, m9, m3, m8, m5, m20, m10]","r":"[]","fam":"fam1","prio":"1"},
{"name":"t88","dur":"363","m":"[]","r":"[]","fam":"fam1","prio":"1"},
{"name":"t89","dur":"591","m":"[]","r":"[]","fam":"fam1","prio":"1"},
{"name":"t90","dur":"168","m":"[m6, m2]","r":"[]","fam":"fam1","prio":"1"},
{"name":"t91","dur":"199","m":"[m14, m10, m16, m4]","r":"[]","fam":"fam1","prio":"1"},
{"name":"t92","dur":"537","m":"[]","r":"[]","fam":"fam1","prio":"1"},
{"name":"t93","dur":"673","m":"[]","r":"[]","fam":"fam1","prio":"1"},
{"name":"t94","dur":"363","m":"[]","r":"[]","fam":"fam1","prio":"1"},
{"name":"t95","dur":"603","m":"[m4, m20, m9, m15, m13, m17, m11, m5]","r":"[]","fam":"fam1","prio":"1"},
{"name":"t96","dur":"153","m":"[]","r":"[]","fam":"fam1","prio":"1"},
{"name":"t97","dur":"87","m":"[]","r":"[r2]","fam":"fam1","prio":"1"},
{"name":"t98","dur":"411","m":"[m7, m4, m2, m20]","r":"[r1]","fam":"fam1","prio":"1"},
{"name":"t99","dur":"361","m":"[]","r":"[]","fam":"fam1","prio":"1"},
{"name":"t100","dur":"608","m":"[]","r":"[r2, r3, r1]","fam":"fam1","prio":"1"}],
"boards":[
"m1",
"m2",
"m3",
"m4",
"m5",
"m6",
"m7",
"m8",
"m9",
"m10",
"m11",
"m12",
"m13",
"m14",
"m15",
"m16",
"m17",
"m18",
"m19",
"m20"],
"resources":[
{"name":"r1","qty":1},
{"name":"r2","qty":1},
{"name":"r3","qty":1}],
"name":"t100m20r3-18.pl"
}
