{"test":[
{"name":"t1","dur":"66","m":"[]","r":"[]","fam":"fam1","prio":"1"},
{"name":"t2","dur":"342","m":"[]","r":"[]","fam":"fam1","prio":"1"},
{"name":"t3","dur":"224","m":"[]","r":"[r3, r4, r8, r7, r9, r5]","fam":"fam1","prio":"1"},
{"name":"t4","dur":"146","m":"[]","r":"[]","fam":"fam1","prio":"1"},
{"name":"t5","dur":"133","m":"[]","r":"[r3, r10, r2]","fam":"fam1","prio":"1"},
{"name":"t6","dur":"344","m":"[]","r":"[]","fam":"fam1","prio":"1"},
{"name":"t7","dur":"485","m":"[]","r":"[r2, r9]","fam":"fam1","prio":"1"},
{"name":"t8","dur":"199","m":"[]","r":"[r2, r1, r7, r9, r3, r4]","fam":"fam1","prio":"1"},
{"name":"t9","dur":"296","m":"[]","r":"[r2]","fam":"fam1","prio":"1"},
{"name":"t10","dur":"116","m":"[]","r":"[]","fam":"fam1","prio":"1"},
{"name":"t11","dur":"242","m":"[]","r":"[]","fam":"fam1","prio":"1"},
{"name":"t12","dur":"670","m":"[m15, m8]","r":"[]","fam":"fam1","prio":"1"},
{"name":"t13","dur":"437","m":"[]","r":"[r9, r3, r1, r10, r8, r6, r5, r7, r4, r2]","fam":"fam1","prio":"1"},
{"name":"t14","dur":"81","m":"[]","r":"[r7, r9, r8, r5, r2, r3, r4, r1]","fam":"fam1","prio":"1"},
{"name":"t15","dur":"600","m":"[m14, m3]","r":"[r6, r4, r3, r1]","fam":"fam1","prio":"1"},
{"name":"t16","dur":"715","m":"[]","r":"[]","fam":"fam1","prio":"1"},
{"name":"t17","dur":"326","m":"[]","r":"[]","fam":"fam1","prio":"1"},
{"name":"t18","dur":"699","m":"[]","r":"[]","fam":"fam1","prio":"1"},
{"name":"t19","dur":"180","m":"[m15, m12, m14, m9, m7, m6, m4, m10]","r":"[r3, r7, r1, r6, r10]","fam":"fam1","prio":"1"},
{"name":"t20","dur":"260","m":"[]","r":"[]","fam":"fam1","prio":"1"},
{"name":"t21","dur":"370","m":"[]","r":"[]","fam":"fam1","prio":"1"},
{"name":"t22","dur":"370","m":"[]","r":"[]","fam":"fam1","prio":"1"},
{"name":"t23","dur":"622","m":"[]","r":"[]","fam":"fam1","prio":"1"},
{"name":"t24","dur":"736","m":"[]","r":"[r6, r9, r5, r4, r1, r2, r7, r3, r10]","fam":"fam1","prio":"1"},
{"name":"t25","dur":"400","m":"[m8, m18, m12, m6, m3]","r":"[]","fam":"fam1","prio":"1"},
{"name":"t26","dur":"439","m":"[]","r":"[r3, r4, r7]","fam":"fam1","prio":"1"},
{"name":"t27","dur":"362","m":"[]","r":"[]","fam":"fam1","prio":"1"},
{"name":"t28","dur":"46","m":"[]","r":"[]","fam":"fam1","prio":"1"},
{"name":"t29","dur":"45","m":"[]","r":"[]","fam":"fam1","prio":"1"},
{"name":"t30","dur":"98","m":"[]","r":"[]","fam":"fam1","prio":"1"},
{"name":"t31","dur":"51","m":"[m7, m13, m15, m20, m1, m3, m14, m19]","r":"[]","fam":"fam1","prio":"1"},
{"name":"t32","dur":"328","m":"[m4, m6, m5, m12, m2, m14, m3]","r":"[]","fam":"fam1","prio":"1"},
{"name":"t33","dur":"590","m":"[]","r":"[]","fam":"fam1","prio":"1"},
{"name":"t34","dur":"301","m":"[]","r":"[]","fam":"fam1","prio":"1"},
{"name":"t35","dur":"327","m":"[]","r":"[]","fam":"fam1","prio":"1"},
{"name":"t36","dur":"680","m":"[]","r":"[]","fam":"fam1","prio":"1"},
{"name":"t37","dur":"95","m":"[]","r":"[r2, r8, r4, r6, r7, r5, r3, r1, r10, r9]","fam":"fam1","prio":"1"},
{"name":"t38","dur":"179","m":"[m15, m17, m5, m13, m14, m18, m1]","r":"[r10, r9, r7, r8]","fam":"fam1","prio":"1"},
{"name":"t39","dur":"184","m":"[]","r":"[]","fam":"fam1","prio":"1"},
{"name":"t40","dur":"513","m":"[m18, m11, m19, m20]","r":"[]","fam":"fam1","prio":"1"},
{"name":"t41","dur":"176","m":"[]","r":"[]","fam":"fam1","prio":"1"},
{"name":"t42","dur":"601","m":"[]","r":"[]","fam":"fam1","prio":"1"},
{"name":"t43","dur":"503","m":"[]","r":"[]","fam":"fam1","prio":"1"},
{"name":"t44","dur":"763","m":"[]","r":"[]","fam":"fam1","prio":"1"},
{"name":"t45","dur":"554","m":"[]","r":"[]","fam":"fam1","prio":"1"},
{"name":"t46","dur":"469","m":"[]","r":"[]","fam":"fam1","prio":"1"},
{"name":"t47","dur":"728","m":"[]","r":"[]","fam":"fam1","prio":"1"},
{"name":"t48","dur":"540","m":"[]","r":"[]","fam":"fam1","prio":"1"},
{"name":"t49","dur":"465","m":"[]","r":"[]","fam":"fam1","prio":"1"},
{"name":"t50","dur":"688","m":"[m4, m20, m19, m12, m15]","r":"[]","fam":"fam1","prio":"1"},
{"name":"t51","dur":"394","m":"[m6, m2, m1, m14, m15, m7, m16, m18]","r":"[r9, r10, r1]","fam":"fam1","prio":"1"},
{"name":"t52","dur":"535","m":"[]","r":"[]","fam":"fam1","prio":"1"},
{"name":"t53","dur":"555","m":"[]","r":"[]","fam":"fam1","prio":"1"},
{"name":"t54","dur":"274","m":"[]","r":"[r9, r5, r3, r2, r1, r4, r10, r7]","fam":"fam1","prio":"1"},
{"name":"t55","dur":"290","m":"[]","r":"[]","fam":"fam1","prio":"1"},
{"name":"t56","dur":"65","m":"[m15, m17, m6, m19, m4]","r":"[r2, r8, r5, r6, r10]","fam":"fam1","prio":"1"},
{"name":"t57","dur":"292","m":"[m4, m20, m18, m15, m19, m17, m8]","r":"[]","fam":"fam1","prio":"1"},
{"name":"t58","dur":"232","m":"[]","r":"[]","fam":"fam1","prio":"1"},
{"name":"t59","dur":"161","m":"[]","r":"[]","fam":"fam1","prio":"1"},
{"name":"t60","dur":"460","m":"[]","r":"[r8, r3, r10, r9, r1]","fam":"fam1","prio":"1"},
{"name":"t61","dur":"196","m":"[]","r":"[]","fam":"fam1","prio":"1"},
{"name":"t62","dur":"417","m":"[]","r":"[]","fam":"fam1","prio":"1"},
{"name":"t63","dur":"480","m":"[m17, m7, m18, m6, m19, m15, m14, m9]","r":"[]","fam":"fam1","prio":"1"},
{"name":"t64","dur":"60","m":"[]","r":"[]","fam":"fam1","prio":"1"},
{"name":"t65","dur":"43","m":"[]","r":"[r9, r3, r8, r7, r5, r1, r10, r6, r2]","fam":"fam1","prio":"1"},
{"name":"t66","dur":"72","m":"[m19, m14, m5, m10, m18, m13, m3]","r":"[r1, r4, r6, r3, r8, r9, r10, r2, r5]","fam":"fam1","prio":"1"},
{"name":"t67","dur":"735","m":"[]","r":"[r5]","fam":"fam1","prio":"1"},
{"name":"t68","dur":"536","m":"[]","r":"[]","fam":"fam1","prio":"1"},
{"name":"t69","dur":"25","m":"[]","r":"[]","fam":"fam1","prio":"1"},
{"name":"t70","dur":"83","m":"[]","r":"[r6, r5, r2]","fam":"fam1","prio":"1"},
{"name":"t71","dur":"549","m":"[]","r":"[]","fam":"fam1","prio":"1"},
{"name":"t72","dur":"565","m":"[m16, m11, m5, m19, m14, m18, m10]","r":"[]","fam":"fam1","prio":"1"},
{"name":"t73","dur":"149","m":"[]","r":"[]","fam":"fam1","prio":"1"},
{"name":"t74","dur":"564","m":"[m11, m9, m14, m6, m17, m7, m1]","r":"[]","fam":"fam1","prio":"1"},
{"name":"t75","dur":"321","m":"[]","r":"[]","fam":"fam1","prio":"1"},
{"name":"t76","dur":"256","m":"[]","r":"[]","fam":"fam1","prio":"1"},
{"name":"t77","dur":"61","m":"[]","r":"[]","fam":"fam1","prio":"1"},
{"name":"t78","dur":"3","m":"[]","r":"[]","fam":"fam1","prio":"1"},
{"name":"t79","dur":"735","m":"[]","r":"[]","fam":"fam1","prio":"1"},
{"name":"t80","dur":"247","m":"[]","r":"[r8, r5, r9, r7, r6, r2, r10, r1, r3, r4]","fam":"fam1","prio":"1"},
{"name":"t81","dur":"109","m":"[]","r":"[]","fam":"fam1","prio":"1"},
{"name":"t82","dur":"625","m":"[]","r":"[]","fam":"fam1","prio":"1"},
{"name":"t83","dur":"799","m":"[]","r":"[]","fam":"fam1","prio":"1"},
{"name":"t84","dur":"374","m":"[]","r":"[]","fam":"fam1","prio":"1"},
{"name":"t85","dur":"764","m":"[]","r":"[r2, r8, r4, r9, r5]","fam":"fam1","prio":"1"},
{"name":"t86","dur":"173","m":"[]","r":"[]","fam":"fam1","prio":"1"},
{"name":"t87","dur":"651","m":"[]","r":"[]","fam":"fam1","prio":"1"},
{"name":"t88","dur":"562","m":"[]","r":"[]","fam":"fam1","prio":"1"},
{"name":"t89","dur":"329","m":"[m13, m1, m10, m9, m7, m19, m8, m18]","r":"[]","fam":"fam1","prio":"1"},
{"name":"t90","dur":"476","m":"[]","r":"[]","fam":"fam1","prio":"1"},
{"name":"t91","dur":"193","m":"[]","r":"[]","fam":"fam1","prio":"1"},
{"name":"t92","dur":"723","m":"[]","r":"[r2, r8, r5, r6, r1, r10, r7, r9, r4, r3]","fam":"fam1","prio":"1"},
{"name":"t93","dur":"332","m":"[]","r":"[r3, r1, r9, r5, r4, r2, r10, r6, r7]","fam":"fam1","prio":"1"},
{"name":"t94","dur":"291","m":"[]","r":"[r5, r10, r6, r8, r1, r7, r4, r2, r9]","fam":"fam1","prio":"1"},
{"name":"t95","dur":"719","m":"[m2, m13, m20, m4, m1, m5]","r":"[r8]","fam":"fam1","prio":"1"},
{"name":"t96","dur":"369","m":"[]","r":"[]","fam":"fam1","prio":"1"},
{"name":"t97","dur":"253","m":"[m9, m2, m8, m20]","r":"[]","fam":"fam1","prio":"1"},
{"name":"t98","dur":"297","m":"[]","r":"[r8]","fam":"fam1","prio":"1"},
{"name":"t99","dur":"230","m":"[m19]","r":"[]","fam":"fam1","prio":"1"},
{"name":"t100","dur":"265","m":"[]","r":"[r2, r9, r5, r6, r4, r10, r1, r8]","fam":"fam1","prio":"1"},
{"name":"t101","dur":"420","m":"[]","r":"[]","fam":"fam1","prio":"1"},
{"name":"t102","dur":"312","m":"[m11, m7, m5, m20, m16, m14, m1, m15]","r":"[]","fam":"fam1","prio":"1"},
{"name":"t103","dur":"312","m":"[]","r":"[]","fam":"fam1","prio":"1"},
{"name":"t104","dur":"270","m":"[]","r":"[r1, r2, r6]","fam":"fam1","prio":"1"},
{"name":"t105","dur":"284","m":"[]","r":"[]","fam":"fam1","prio":"1"},
{"name":"t106","dur":"761","m":"[m11, m15, m14, m16, m1, m2, m19]","r":"[]","fam":"fam1","prio":"1"},
{"name":"t107","dur":"30","m":"[]","r":"[]","fam":"fam1","prio":"1"},
{"name":"t108","dur":"661","m":"[]","r":"[]","fam":"fam1","prio":"1"},
{"name":"t109","dur":"536","m":"[]","r":"[]","fam":"fam1","prio":"1"},
{"name":"t110","dur":"54","m":"[]","r":"[]","fam":"fam1","prio":"1"},
{"name":"t111","dur":"609","m":"[]","r":"[]","fam":"fam1","prio":"1"},
{"name":"t112","dur":"455","m":"[]","r":"[]","fam":"fam1","prio":"1"},
{"name":"t113","dur":"194","m":"[]","r":"[]","fam":"fam1","prio":"1"},
{"name":"t114","dur":"79","m":"[]","r":"[]","fam":"fam1","prio":"1"},
{"name":"t115","dur":"310","m":"[m18, m14, m5]","r":"[r8]","fam":"fam1","prio":"1"},
{"name":"t116","dur":"644","m":"[]","r":"[]","fam":"fam1","prio":"1"},
{"name":"t117","dur":"86","m":"[]","r":"[]","fam":"fam1","prio":"1"},
{"name":"t118","dur":"79","m":"[m11, m13, m12, m16, m7]","r":"[]","fam":"fam1","prio":"1"},
{"name":"t119","dur":"380","m":"[]","r":"[]","fam":"fam1","prio":"1"},
{"name":"t120","dur":"500","m":"[m7, m14, m10, m5, m13, m8]","r":"[r3, r1, r7, r6, r4, r5, r2]","fam":"fam1","prio":"1"},
{"name":"t121","dur":"265","m":"[]","r":"[r8, r1, r10, r7, r6, r5]","fam":"fam1","prio":"1"},
{"name":"t122","dur":"13","m":"[]","r":"[r3, r9, r5, r7, r10, r6, r8, r2, r1]","fam":"fam1","prio":"1"},
{"name":"t123","dur":"460","m":"[]","r":"[]","fam":"fam1","prio":"1"},
{"name":"t124","dur":"681","m":"[]","r":"[r2]","fam":"fam1","prio":"1"},
{"name":"t125","dur":"360","m":"[]","r":"[r10, r9, r5, r1, r3]","fam":"fam1","prio":"1"},
{"name":"t126","dur":"789","m":"[m10, m4, m12]","r":"[]","fam":"fam1","prio":"1"},
{"name":"t127","dur":"688","m":"[]","r":"[]","fam":"fam1","prio":"1"},
{"name":"t128","dur":"675","m":"[]","r":"[]","fam":"fam1","prio":"1"},
{"name":"t129","dur":"627","m":"[]","r":"[r2, r4, r8, r10]","fam":"fam1","prio":"1"},
{"name":"t130","dur":"585","m":"[m9]","r":"[]","fam":"fam1","prio":"1"},
{"name":"t131","dur":"801","m":"[]","r":"[r7, r2, r4]","fam":"fam1","prio":"1"},
{"name":"t132","dur":"148","m":"[m13, m20, m12, m18, m11, m17, m6, m9]","r":"[]","fam":"fam1","prio":"1"},
{"name":"t133","dur":"139","m":"[m10]","r":"[]","fam":"fam1","prio":"1"},
{"name":"t134","dur":"83","m":"[]","r":"[]","fam":"fam1","prio":"1"},
{"name":"t135","dur":"121","m":"[]","r":"[]","fam":"fam1","prio":"1"},
{"name":"t136","dur":"773","m":"[]","r":"[]","fam":"fam1","prio":"1"},
{"name":"t137","dur":"733","m":"[]","r":"[]","fam":"fam1","prio":"1"},
{"name":"t138","dur":"265","m":"[]","r":"[]","fam":"fam1","prio":"1"},
{"name":"t139","dur":"45","m":"[]","r":"[r3, r5, r10, r4, r9, r8, r2, r7, r6, r1]","fam":"fam1","prio":"1"},
{"name":"t140","dur":"384","m":"[]","r":"[r10, r6, r4, r1, r8, r5, r9]","fam":"fam1","prio":"1"},
{"name":"t141","dur":"249","m":"[]","r":"[]","fam":"fam1","prio":"1"},
{"name":"t142","dur":"661","m":"[]","r":"[]","fam":"fam1","prio":"1"},
{"name":"t143","dur":"669","m":"[]","r":"[]","fam":"fam1","prio":"1"},
{"name":"t144","dur":"504","m":"[]","r":"[r10, r2, r5]","fam":"fam1","prio":"1"},
{"name":"t145","dur":"151","m":"[]","r":"[]","fam":"fam1","prio":"1"},
{"name":"t146","dur":"690","m":"[]","r":"[]","fam":"fam1","prio":"1"},
{"name":"t147","dur":"43","m":"[m17, m3, m7, m19, m4]","r":"[]","fam":"fam1","prio":"1"},
{"name":"t148","dur":"642","m":"[]","r":"[r4, r3, r8, r6, r9, r5, r1, r7, r2]","fam":"fam1","prio":"1"},
{"name":"t149","dur":"654","m":"[m13, m10, m17, m2]","r":"[]","fam":"fam1","prio":"1"},
{"name":"t150","dur":"222","m":"[]","r":"[]","fam":"fam1","prio":"1"},
{"name":"t151","dur":"351","m":"[]","r":"[]","fam":"fam1","prio":"1"},
{"name":"t152","dur":"632","m":"[m1, m16, m17]","r":"[]","fam":"fam1","prio":"1"},
{"name":"t153","dur":"591","m":"[]","r":"[]","fam":"fam1","prio":"1"},
{"name":"t154","dur":"582","m":"[]","r":"[]","fam":"fam1","prio":"1"},
{"name":"t155","dur":"777","m":"[]","r":"[r10, r6, r1, r3, r4]","fam":"fam1","prio":"1"},
{"name":"t156","dur":"260","m":"[]","r":"[]","fam":"fam1","prio":"1"},
{"name":"t157","dur":"669","m":"[m8, m18, m4, m19, m5, m13, m20, m7]","r":"[r5, r2, r3]","fam":"fam1","prio":"1"},
{"name":"t158","dur":"757","m":"[]","r":"[]","fam":"fam1","prio":"1"},
{"name":"t159","dur":"447","m":"[]","r":"[]","fam":"fam1","prio":"1"},
{"name":"t160","dur":"66","m":"[m17, m2, m6, m11]","r":"[]","fam":"fam1","prio":"1"},
{"name":"t161","dur":"99","m":"[]","r":"[]","fam":"fam1","prio":"1"},
{"name":"t162","dur":"605","m":"[m18, m9, m17, m15]","r":"[]","fam":"fam1","prio":"1"},
{"name":"t163","dur":"6","m":"[]","r":"[r8, r1, r3, r5, r4]","fam":"fam1","prio":"1"},
{"name":"t164","dur":"771","m":"[m20, m18, m6, m2, m10, m9, m3]","r":"[]","fam":"fam1","prio":"1"},
{"name":"t165","dur":"522","m":"[]","r":"[]","fam":"fam1","prio":"1"},
{"name":"t166","dur":"201","m":"[]","r":"[]","fam":"fam1","prio":"1"},
{"name":"t167","dur":"670","m":"[m12, m14, m11, m9, m17, m10]","r":"[]","fam":"fam1","prio":"1"},
{"name":"t168","dur":"434","m":"[m12, m10, m7, m20, m16]","r":"[]","fam":"fam1","prio":"1"},
{"name":"t169","dur":"563","m":"[]","r":"[]","fam":"fam1","prio":"1"},
{"name":"t170","dur":"507","m":"[m1, m16, m11, m3, m9, m15]","r":"[r1, r5, r10]","fam":"fam1","prio":"1"},
{"name":"t171","dur":"396","m":"[]","r":"[]","fam":"fam1","prio":"1"},
{"name":"t172","dur":"159","m":"[]","r":"[]","fam":"fam1","prio":"1"},
{"name":"t173","dur":"356","m":"[]","r":"[]","fam":"fam1","prio":"1"},
{"name":"t174","dur":"472","m":"[m8, m1, m13, m9, m11, m10, m18]","r":"[]","fam":"fam1","prio":"1"},
{"name":"t175","dur":"592","m":"[]","r":"[]","fam":"fam1","prio":"1"},
{"name":"t176","dur":"779","m":"[m2]","r":"[]","fam":"fam1","prio":"1"},
{"name":"t177","dur":"273","m":"[m16, m19, m8, m2]","r":"[]","fam":"fam1","prio":"1"},
{"name":"t178","dur":"131","m":"[]","r":"[r9, r5, r2, r10, r8, r4]","fam":"fam1","prio":"1"},
{"name":"t179","dur":"272","m":"[]","r":"[]","fam":"fam1","prio":"1"},
{"name":"t180","dur":"728","m":"[]","r":"[]","fam":"fam1","prio":"1"},
{"name":"t181","dur":"728","m":"[]","r":"[]","fam":"fam1","prio":"1"},
{"name":"t182","dur":"48","m":"[]","r":"[]","fam":"fam1","prio":"1"},
{"name":"t183","dur":"779","m":"[m2, m10, m13, m20, m11, m4]","r":"[]","fam":"fam1","prio":"1"},
{"name":"t184","dur":"391","m":"[m15, m17, m6, m3, m2]","r":"[]","fam":"fam1","prio":"1"},
{"name":"t185","dur":"717","m":"[]","r":"[]","fam":"fam1","prio":"1"},
{"name":"t186","dur":"46","m":"[m8, m4, m6, m9, m3]","r":"[]","fam":"fam1","prio":"1"},
{"name":"t187","dur":"578","m":"[]","r":"[r7, r3, r9, r2, r4, r8, r10, r1, r6]","fam":"fam1","prio":"1"},
{"name":"t188","dur":"146","m":"[]","r":"[]","fam":"fam1","prio":"1"},
{"name":"t189","dur":"79","m":"[]","r":"[]","fam":"fam1","prio":"1"},
{"name":"t190","dur":"631","m":"[]","r":"[r9, r7, r3]","fam":"fam1","prio":"1"},
{"name":"t191","dur":"760","m":"[]","r":"[]","fam":"fam1","prio":"1"},
{"name":"t192","dur":"228","m":"[]","r":"[]","fam":"fam1","prio":"1"},
{"name":"t193","dur":"293","m":"[]","r":"[]","fam":"fam1","prio":"1"},
{"name":"t194","dur":"63","m":"[]","r":"[r9, r10, r6, r2, r5]","fam":"fam1","prio":"1"},
{"name":"t195","dur":"589","m":"[m1, m14, m8]","r":"[r6, r7, r1, r10, r3, r4, r2, r9, r8]","fam":"fam1","prio":"1"},
{"name":"t196","dur":"36","m":"[]","r":"[r5, r6, r3, r2, r8, r7, r10, r9, r1, r4]","fam":"fam1","prio":"1"},
{"name":"t197","dur":"290","m":"[m20, m5, m14, m13]","r":"[]","fam":"fam1","prio":"1"},
{"name":"t198","dur":"159","m":"[m12, m15]","r":"[r10, r5, r6, r8, r1, r7, r2, r4]","fam":"fam1","prio":"1"},
{"name":"t199","dur":"268","m":"[]","r":"[]","fam":"fam1","prio":"1"},
{"name":"t200","dur":"285","m":"[m9, m3, m13]","r":"[]","fam":"fam1","prio":"1"},
{"name":"t201","dur":"308","m":"[m10, m4, m9, m5, m7, m2, m13, m12]","r":"[]","fam":"fam1","prio":"1"},
{"name":"t202","dur":"504","m":"[]","r":"[r9, r7, r3, r8, r4, r5, r10]","fam":"fam1","prio":"1"},
{"name":"t203","dur":"564","m":"[]","r":"[r9]","fam":"fam1","prio":"1"},
{"name":"t204","dur":"566","m":"[m14, m6]","r":"[]","fam":"fam1","prio":"1"},
{"name":"t205","dur":"424","m":"[]","r":"[]","fam":"fam1","prio":"1"},
{"name":"t206","dur":"312","m":"[]","r":"[r3, r7, r8, r1, r9, r5, r10, r4, r2]","fam":"fam1","prio":"1"},
{"name":"t207","dur":"465","m":"[]","r":"[r2, r4, r7, r5, r6, r10, r8, r9, r1]","fam":"fam1","prio":"1"},
{"name":"t208","dur":"374","m":"[]","r":"[r8, r1, r3, r4, r10, r9, r5, r2, r7]","fam":"fam1","prio":"1"},
{"name":"t209","dur":"424","m":"[]","r":"[]","fam":"fam1","prio":"1"},
{"name":"t210","dur":"177","m":"[m11, m12, m18, m6, m17, m4]","r":"[]","fam":"fam1","prio":"1"},
{"name":"t211","dur":"116","m":"[m1, m5, m11]","r":"[]","fam":"fam1","prio":"1"},
{"name":"t212","dur":"158","m":"[]","r":"[r5, r3, r2, r1, r6, r10, r7]","fam":"fam1","prio":"1"},
{"name":"t213","dur":"53","m":"[]","r":"[]","fam":"fam1","prio":"1"},
{"name":"t214","dur":"618","m":"[]","r":"[]","fam":"fam1","prio":"1"},
{"name":"t215","dur":"38","m":"[]","r":"[]","fam":"fam1","prio":"1"},
{"name":"t216","dur":"309","m":"[]","r":"[]","fam":"fam1","prio":"1"},
{"name":"t217","dur":"657","m":"[]","r":"[]","fam":"fam1","prio":"1"},
{"name":"t218","dur":"321","m":"[]","r":"[r5, r9, r2, r4]","fam":"fam1","prio":"1"},
{"name":"t219","dur":"609","m":"[m14, m1, m19, m10, m3, m4]","r":"[]","fam":"fam1","prio":"1"},
{"name":"t220","dur":"582","m":"[]","r":"[]","fam":"fam1","prio":"1"},
{"name":"t221","dur":"524","m":"[]","r":"[]","fam":"fam1","prio":"1"},
{"name":"t222","dur":"722","m":"[m9, m1, m7, m16, m6, m5, m3, m2]","r":"[]","fam":"fam1","prio":"1"},
{"name":"t223","dur":"496","m":"[]","r":"[]","fam":"fam1","prio":"1"},
{"name":"t224","dur":"40","m":"[m16]","r":"[]","fam":"fam1","prio":"1"},
{"name":"t225","dur":"256","m":"[]","r":"[]","fam":"fam1","prio":"1"},
{"name":"t226","dur":"399","m":"[]","r":"[r5, r4, r8, r1, r7, r2, r10, r9, r6]","fam":"fam1","prio":"1"},
{"name":"t227","dur":"450","m":"[]","r":"[]","fam":"fam1","prio":"1"},
{"name":"t228","dur":"178","m":"[]","r":"[]","fam":"fam1","prio":"1"},
{"name":"t229","dur":"536","m":"[]","r":"[r2]","fam":"fam1","prio":"1"},
{"name":"t230","dur":"648","m":"[]","r":"[]","fam":"fam1","prio":"1"},
{"name":"t231","dur":"509","m":"[]","r":"[]","fam":"fam1","prio":"1"},
{"name":"t232","dur":"333","m":"[]","r":"[]","fam":"fam1","prio":"1"},
{"name":"t233","dur":"152","m":"[]","r":"[]","fam":"fam1","prio":"1"},
{"name":"t234","dur":"416","m":"[]","r":"[r9, r2, r3, r10, r7, r5]","fam":"fam1","prio":"1"},
{"name":"t235","dur":"577","m":"[]","r":"[r3, r7]","fam":"fam1","prio":"1"},
{"name":"t236","dur":"511","m":"[]","r":"[]","fam":"fam1","prio":"1"},
{"name":"t237","dur":"765","m":"[]","r":"[r10, r2, r3, r4, r7, r5, r9, r8, r1]","fam":"fam1","prio":"1"},
{"name":"t238","dur":"534","m":"[]","r":"[]","fam":"fam1","prio":"1"},
{"name":"t239","dur":"308","m":"[]","r":"[]","fam":"fam1","prio":"1"},
{"name":"t240","dur":"377","m":"[]","r":"[]","fam":"fam1","prio":"1"},
{"name":"t241","dur":"259","m":"[]","r":"[]","fam":"fam1","prio":"1"},
{"name":"t242","dur":"253","m":"[]","r":"[]","fam":"fam1","prio":"1"},
{"name":"t243","dur":"343","m":"[]","r":"[r5, r6, r2, r9]","fam":"fam1","prio":"1"},
{"name":"t244","dur":"254","m":"[m18, m3, m17, m12, m16, m9, m13]","r":"[r3, r2, r1, r4, r6]","fam":"fam1","prio":"1"},
{"name":"t245","dur":"22","m":"[]","r":"[]","fam":"fam1","prio":"1"},
{"name":"t246","dur":"454","m":"[]","r":"[]","fam":"fam1","prio":"1"},
{"name":"t247","dur":"378","m":"[]","r":"[]","fam":"fam1","prio":"1"},
{"name":"t248","dur":"437","m":"[]","r":"[]","fam":"fam1","prio":"1"},
{"name":"t249","dur":"173","m":"[]","r":"[r6, r1]","fam":"fam1","prio":"1"},
{"name":"t250","dur":"196","m":"[]","r":"[]","fam":"fam1","prio":"1"},
{"name":"t251","dur":"627","m":"[]","r":"[]","fam":"fam1","prio":"1"},
{"name":"t252","dur":"204","m":"[]","r":"[r8, r9, r6, r10]","fam":"fam1","prio":"1"},
{"name":"t253","dur":"384","m":"[]","r":"[]","fam":"fam1","prio":"1"},
{"name":"t254","dur":"531","m":"[]","r":"[]","fam":"fam1","prio":"1"},
{"name":"t255","dur":"327","m":"[]","r":"[]","fam":"fam1","prio":"1"},
{"name":"t256","dur":"595","m":"[]","r":"[]","fam":"fam1","prio":"1"},
{"name":"t257","dur":"362","m":"[]","r":"[]","fam":"fam1","prio":"1"},
{"name":"t258","dur":"432","m":"[]","r":"[]","fam":"fam1","prio":"1"},
{"name":"t259","dur":"57","m":"[]","r":"[]","fam":"fam1","prio":"1"},
{"name":"t260","dur":"225","m":"[]","r":"[r4, r7, r1, r5, r3, r10, r8]","fam":"fam1","prio":"1"},
{"name":"t261","dur":"760","m":"[]","r":"[]","fam":"fam1","prio":"1"},
{"name":"t262","dur":"141","m":"[]","r":"[]","fam":"fam1","prio":"1"},
{"name":"t263","dur":"37","m":"[]","r":"[r3, r8, r10, r9, r7, r6]","fam":"fam1","prio":"1"},
{"name":"t264","dur":"314","m":"[]","r":"[]","fam":"fam1","prio":"1"},
{"name":"t265","dur":"114","m":"[m5, m15]","r":"[]","fam":"fam1","prio":"1"},
{"name":"t266","dur":"720","m":"[]","r":"[r6, r5, r10, r3, r1, r2, r7, r9, r8, r4]","fam":"fam1","prio":"1"},
{"name":"t267","dur":"710","m":"[]","r":"[]","fam":"fam1","prio":"1"},
{"name":"t268","dur":"239","m":"[]","r":"[]","fam":"fam1","prio":"1"},
{"name":"t269","dur":"604","m":"[m16, m8, m13, m3]","r":"[]","fam":"fam1","prio":"1"},
{"name":"t270","dur":"601","m":"[]","r":"[]","fam":"fam1","prio":"1"},
{"name":"t271","dur":"404","m":"[]","r":"[]","fam":"fam1","prio":"1"},
{"name":"t272","dur":"673","m":"[]","r":"[]","fam":"fam1","prio":"1"},
{"name":"t273","dur":"757","m":"[]","r":"[]","fam":"fam1","prio":"1"},
{"name":"t274","dur":"150","m":"[]","r":"[]","fam":"fam1","prio":"1"},
{"name":"t275","dur":"537","m":"[]","r":"[]","fam":"fam1","prio":"1"},
{"name":"t276","dur":"698","m":"[]","r":"[]","fam":"fam1","prio":"1"},
{"name":"t277","dur":"488","m":"[]","r":"[]","fam":"fam1","prio":"1"},
{"name":"t278","dur":"131","m":"[m17, m15, m7, m4, m18, m13, m5, m8]","r":"[]","fam":"fam1","prio":"1"},
{"name":"t279","dur":"780","m":"[]","r":"[]","fam":"fam1","prio":"1"},
{"name":"t280","dur":"647","m":"[m15, m10, m19, m1, m17]","r":"[]","fam":"fam1","prio":"1"},
{"name":"t281","dur":"684","m":"[]","r":"[r4, r2, r5, r3, r1, r6]","fam":"fam1","prio":"1"},
{"name":"t282","dur":"460","m":"[]","r":"[]","fam":"fam1","prio":"1"},
{"name":"t283","dur":"613","m":"[]","r":"[]","fam":"fam1","prio":"1"},
{"name":"t284","dur":"7","m":"[]","r":"[r1, r9, r5]","fam":"fam1","prio":"1"},
{"name":"t285","dur":"500","m":"[]","r":"[]","fam":"fam1","prio":"1"},
{"name":"t286","dur":"760","m":"[m8, m9, m10, m18, m2, m19]","r":"[]","fam":"fam1","prio":"1"},
{"name":"t287","dur":"739","m":"[m18, m20, m10, m13, m5, m4, m19, m17]","r":"[]","fam":"fam1","prio":"1"},
{"name":"t288","dur":"428","m":"[]","r":"[]","fam":"fam1","prio":"1"},
{"name":"t289","dur":"680","m":"[]","r":"[]","fam":"fam1","prio":"1"},
{"name":"t290","dur":"404","m":"[]","r":"[]","fam":"fam1","prio":"1"},
{"name":"t291","dur":"594","m":"[m1]","r":"[r9, r1, r8, r3, r4, r2, r6, r5]","fam":"fam1","prio":"1"},
{"name":"t292","dur":"324","m":"[]","r":"[]","fam":"fam1","prio":"1"},
{"name":"t293","dur":"555","m":"[]","r":"[r6, r10, r5, r1, r7, r9, r4, r8, r3, r2]","fam":"fam1","prio":"1"},
{"name":"t294","dur":"429","m":"[]","r":"[]","fam":"fam1","prio":"1"},
{"name":"t295","dur":"699","m":"[]","r":"[r1, r7, r3, r8, r2, r6, r5]","fam":"fam1","prio":"1"},
{"name":"t296","dur":"235","m":"[m2, m19, m3, m11, m18]","r":"[]","fam":"fam1","prio":"1"},
{"name":"t297","dur":"382","m":"[]","r":"[]","fam":"fam1","prio":"1"},
{"name":"t298","dur":"511","m":"[]","r":"[]","fam":"fam1","prio":"1"},
{"name":"t299","dur":"39","m":"[]","r":"[r7, r1, r5, r10, r8, r3, r9, r2, r4]","fam":"fam1","prio":"1"},
{"name":"t300","dur":"707","m":"[]","r":"[]","fam":"fam1","prio":"1"},
{"name":"t301","dur":"288","m":"[m11]","r":"[]","fam":"fam1","prio":"1"},
{"name":"t302","dur":"671","m":"[m15, m14, m16, m10, m3]","r":"[]","fam":"fam1","prio":"1"},
{"name":"t303","dur":"222","m":"[]","r":"[]","fam":"fam1","prio":"1"},
{"name":"t304","dur":"170","m":"[]","r":"[]","fam":"fam1","prio":"1"},
{"name":"t305","dur":"314","m":"[]","r":"[]","fam":"fam1","prio":"1"},
{"name":"t306","dur":"571","m":"[]","r":"[]","fam":"fam1","prio":"1"},
{"name":"t307","dur":"460","m":"[m6]","r":"[]","fam":"fam1","prio":"1"},
{"name":"t308","dur":"551","m":"[]","r":"[r10, r2, r3]","fam":"fam1","prio":"1"},
{"name":"t309","dur":"432","m":"[]","r":"[r8, r7, r10, r4, r3, r2]","fam":"fam1","prio":"1"},
{"name":"t310","dur":"4","m":"[]","r":"[]","fam":"fam1","prio":"1"},
{"name":"t311","dur":"442","m":"[]","r":"[]","fam":"fam1","prio":"1"},
{"name":"t312","dur":"152","m":"[]","r":"[]","fam":"fam1","prio":"1"},
{"name":"t313","dur":"744","m":"[m19, m10, m13]","r":"[]","fam":"fam1","prio":"1"},
{"name":"t314","dur":"134","m":"[]","r":"[r10, r8, r4, r3, r9, r7, r1]","fam":"fam1","prio":"1"},
{"name":"t315","dur":"413","m":"[]","r":"[]","fam":"fam1","prio":"1"},
{"name":"t316","dur":"699","m":"[]","r":"[]","fam":"fam1","prio":"1"},
{"name":"t317","dur":"365","m":"[m16, m17, m6, m8, m3, m10]","r":"[r7, r6, r3]","fam":"fam1","prio":"1"},
{"name":"t318","dur":"118","m":"[]","r":"[]","fam":"fam1","prio":"1"},
{"name":"t319","dur":"234","m":"[m8, m4, m20, m5, m19, m18, m2, m11]","r":"[]","fam":"fam1","prio":"1"},
{"name":"t320","dur":"230","m":"[]","r":"[]","fam":"fam1","prio":"1"},
{"name":"t321","dur":"631","m":"[]","r":"[r6, r2, r7]","fam":"fam1","prio":"1"},
{"name":"t322","dur":"50","m":"[]","r":"[]","fam":"fam1","prio":"1"},
{"name":"t323","dur":"308","m":"[]","r":"[]","fam":"fam1","prio":"1"},
{"name":"t324","dur":"563","m":"[]","r":"[]","fam":"fam1","prio":"1"},
{"name":"t325","dur":"40","m":"[]","r":"[]","fam":"fam1","prio":"1"},
{"name":"t326","dur":"118","m":"[]","r":"[]","fam":"fam1","prio":"1"},
{"name":"t327","dur":"315","m":"[]","r":"[]","fam":"fam1","prio":"1"},
{"name":"t328","dur":"537","m":"[]","r":"[]","fam":"fam1","prio":"1"},
{"name":"t329","dur":"338","m":"[]","r":"[]","fam":"fam1","prio":"1"},
{"name":"t330","dur":"138","m":"[m14, m5, m12]","r":"[]","fam":"fam1","prio":"1"},
{"name":"t331","dur":"503","m":"[]","r":"[r10, r8, r6, r7, r1]","fam":"fam1","prio":"1"},
{"name":"t332","dur":"287","m":"[]","r":"[r3, r2]","fam":"fam1","prio":"1"},
{"name":"t333","dur":"329","m":"[m18, m19, m8, m10, m9, m6, m20, m14]","r":"[]","fam":"fam1","prio":"1"},
{"name":"t334","dur":"799","m":"[]","r":"[r5, r3, r1, r8, r9, r7]","fam":"fam1","prio":"1"},
{"name":"t335","dur":"536","m":"[m11, m5, m12, m4, m19, m15, m7]","r":"[]","fam":"fam1","prio":"1"},
{"name":"t336","dur":"650","m":"[m8, m6, m2, m7, m17, m9, m19, m14]","r":"[]","fam":"fam1","prio":"1"},
{"name":"t337","dur":"446","m":"[m1, m14, m6, m18, m2]","r":"[]","fam":"fam1","prio":"1"},
{"name":"t338","dur":"655","m":"[]","r":"[]","fam":"fam1","prio":"1"},
{"name":"t339","dur":"529","m":"[m15, m12, m5]","r":"[r6]","fam":"fam1","prio":"1"},
{"name":"t340","dur":"736","m":"[]","r":"[]","fam":"fam1","prio":"1"},
{"name":"t341","dur":"501","m":"[]","r":"[]","fam":"fam1","prio":"1"},
{"name":"t342","dur":"173","m":"[]","r":"[]","fam":"fam1","prio":"1"},
{"name":"t343","dur":"452","m":"[]","r":"[r9, r3, r6, r1, r5, r8]","fam":"fam1","prio":"1"},
{"name":"t344","dur":"474","m":"[]","r":"[]","fam":"fam1","prio":"1"},
{"name":"t345","dur":"48","m":"[]","r":"[]","fam":"fam1","prio":"1"},
{"name":"t346","dur":"244","m":"[]","r":"[]","fam":"fam1","prio":"1"},
{"name":"t347","dur":"388","m":"[]","r":"[]","fam":"fam1","prio":"1"},
{"name":"t348","dur":"705","m":"[]","r":"[]","fam":"fam1","prio":"1"},
{"name":"t349","dur":"32","m":"[]","r":"[]","fam":"fam1","prio":"1"},
{"name":"t350","dur":"264","m":"[]","r":"[]","fam":"fam1","prio":"1"},
{"name":"t351","dur":"764","m":"[]","r":"[r3, r1, r8, r10, r7]","fam":"fam1","prio":"1"},
{"name":"t352","dur":"84","m":"[]","r":"[]","fam":"fam1","prio":"1"},
{"name":"t353","dur":"348","m":"[]","r":"[]","fam":"fam1","prio":"1"},
{"name":"t354","dur":"550","m":"[]","r":"[r9, r2, r7, r6, r1, r8, r10, r4]","fam":"fam1","prio":"1"},
{"name":"t355","dur":"358","m":"[]","r":"[r1, r3, r5, r10, r2, r9, r4, r6, r8, r7]","fam":"fam1","prio":"1"},
{"name":"t356","dur":"604","m":"[]","r":"[]","fam":"fam1","prio":"1"},
{"name":"t357","dur":"403","m":"[]","r":"[]","fam":"fam1","prio":"1"},
{"name":"t358","dur":"35","m":"[m20]","r":"[]","fam":"fam1","prio":"1"},
{"name":"t359","dur":"203","m":"[]","r":"[]","fam":"fam1","prio":"1"},
{"name":"t360","dur":"56","m":"[m15, m5, m8, m19, m11, m4, m20]","r":"[]","fam":"fam1","prio":"1"},
{"name":"t361","dur":"130","m":"[]","r":"[]","fam":"fam1","prio":"1"},
{"name":"t362","dur":"654","m":"[]","r":"[]","fam":"fam1","prio":"1"},
{"name":"t363","dur":"364","m":"[]","r":"[r1, r8, r5]","fam":"fam1","prio":"1"},
{"name":"t364","dur":"716","m":"[m3, m16, m8, m14]","r":"[]","fam":"fam1","prio":"1"},
{"name":"t365","dur":"164","m":"[]","r":"[r8, r10]","fam":"fam1","prio":"1"},
{"name":"t366","dur":"481","m":"[]","r":"[r2, r4, r10]","fam":"fam1","prio":"1"},
{"name":"t367","dur":"692","m":"[]","r":"[]","fam":"fam1","prio":"1"},
{"name":"t368","dur":"205","m":"[]","r":"[]","fam":"fam1","prio":"1"},
{"name":"t369","dur":"232","m":"[]","r":"[]","fam":"fam1","prio":"1"},
{"name":"t370","dur":"708","m":"[]","r":"[]","fam":"fam1","prio":"1"},
{"name":"t371","dur":"756","m":"[]","r":"[r5, r4, r7, r10, r6, r3, r9, r2, r1, r8]","fam":"fam1","prio":"1"},
{"name":"t372","dur":"84","m":"[]","r":"[]","fam":"fam1","prio":"1"},
{"name":"t373","dur":"343","m":"[]","r":"[]","fam":"fam1","prio":"1"},
{"name":"t374","dur":"80","m":"[]","r":"[]","fam":"fam1","prio":"1"},
{"name":"t375","dur":"149","m":"[]","r":"[r10, r8, r6]","fam":"fam1","prio":"1"},
{"name":"t376","dur":"712","m":"[]","r":"[r3, r9, r5, r8, r10]","fam":"fam1","prio":"1"},
{"name":"t377","dur":"37","m":"[m16, m7]","r":"[r6, r7, r4, r1, r9, r2]","fam":"fam1","prio":"1"},
{"name":"t378","dur":"117","m":"[]","r":"[]","fam":"fam1","prio":"1"},
{"name":"t379","dur":"55","m":"[]","r":"[]","fam":"fam1","prio":"1"},
{"name":"t380","dur":"569","m":"[]","r":"[]","fam":"fam1","prio":"1"},
{"name":"t381","dur":"187","m":"[]","r":"[]","fam":"fam1","prio":"1"},
{"name":"t382","dur":"497","m":"[]","r":"[r4, r5, r3, r1, r10, r6]","fam":"fam1","prio":"1"},
{"name":"t383","dur":"394","m":"[]","r":"[r2, r1, r6, r10, r8, r9, r4, r5]","fam":"fam1","prio":"1"},
{"name":"t384","dur":"755","m":"[]","r":"[]","fam":"fam1","prio":"1"},
{"name":"t385","dur":"97","m":"[]","r":"[]","fam":"fam1","prio":"1"},
{"name":"t386","dur":"411","m":"[]","r":"[r6, r1, r4, r8, r3, r5, r9, r7]","fam":"fam1","prio":"1"},
{"name":"t387","dur":"309","m":"[]","r":"[]","fam":"fam1","prio":"1"},
{"name":"t388","dur":"284","m":"[m1, m14, m16, m6, m7]","r":"[r9, r8, r2, r7]","fam":"fam1","prio":"1"},
{"name":"t389","dur":"525","m":"[]","r":"[]","fam":"fam1","prio":"1"},
{"name":"t390","dur":"589","m":"[]","r":"[]","fam":"fam1","prio":"1"},
{"name":"t391","dur":"663","m":"[]","r":"[]","fam":"fam1","prio":"1"},
{"name":"t392","dur":"144","m":"[]","r":"[r3]","fam":"fam1","prio":"1"},
{"name":"t393","dur":"512","m":"[]","r":"[]","fam":"fam1","prio":"1"},
{"name":"t394","dur":"478","m":"[]","r":"[]","fam":"fam1","prio":"1"},
{"name":"t395","dur":"475","m":"[]","r":"[r6, r9, r3]","fam":"fam1","prio":"1"},
{"name":"t396","dur":"341","m":"[m5]","r":"[r6, r4, r10, r7]","fam":"fam1","prio":"1"},
{"name":"t397","dur":"117","m":"[]","r":"[]","fam":"fam1","prio":"1"},
{"name":"t398","dur":"421","m":"[]","r":"[]","fam":"fam1","prio":"1"},
{"name":"t399","dur":"497","m":"[m8, m2]","r":"[r8, r1, r9, r4, r3, r2, r5, r6]","fam":"fam1","prio":"1"},
{"name":"t400","dur":"61","m":"[]","r":"[r4]","fam":"fam1","prio":"1"},
{"name":"t401","dur":"610","m":"[m5]","r":"[]","fam":"fam1","prio":"1"},
{"name":"t402","dur":"197","m":"[]","r":"[r7]","fam":"fam1","prio":"1"},
{"name":"t403","dur":"155","m":"[m4, m6, m15, m7]","r":"[]","fam":"fam1","prio":"1"},
{"name":"t404","dur":"659","m":"[m12, m1, m11, m7, m18, m19]","r":"[]","fam":"fam1","prio":"1"},
{"name":"t405","dur":"243","m":"[]","r":"[r8, r3, r10, r2, r1]","fam":"fam1","prio":"1"},
{"name":"t406","dur":"686","m":"[]","r":"[r9, r5, r2, r7, r1, r8, r4, r3, r10]","fam":"fam1","prio":"1"},
{"name":"t407","dur":"681","m":"[]","r":"[]","fam":"fam1","prio":"1"},
{"name":"t408","dur":"750","m":"[]","r":"[r9]","fam":"fam1","prio":"1"},
{"name":"t409","dur":"687","m":"[]","r":"[]","fam":"fam1","prio":"1"},
{"name":"t410","dur":"474","m":"[]","r":"[]","fam":"fam1","prio":"1"},
{"name":"t411","dur":"439","m":"[]","r":"[]","fam":"fam1","prio":"1"},
{"name":"t412","dur":"275","m":"[]","r":"[]","fam":"fam1","prio":"1"},
{"name":"t413","dur":"185","m":"[]","r":"[]","fam":"fam1","prio":"1"},
{"name":"t414","dur":"232","m":"[]","r":"[r5]","fam":"fam1","prio":"1"},
{"name":"t415","dur":"423","m":"[]","r":"[]","fam":"fam1","prio":"1"},
{"name":"t416","dur":"605","m":"[]","r":"[]","fam":"fam1","prio":"1"},
{"name":"t417","dur":"796","m":"[]","r":"[]","fam":"fam1","prio":"1"},
{"name":"t418","dur":"538","m":"[]","r":"[]","fam":"fam1","prio":"1"},
{"name":"t419","dur":"470","m":"[]","r":"[]","fam":"fam1","prio":"1"},
{"name":"t420","dur":"259","m":"[m5, m15, m7, m8, m9, m4, m17]","r":"[]","fam":"fam1","prio":"1"},
{"name":"t421","dur":"784","m":"[]","r":"[]","fam":"fam1","prio":"1"},
{"name":"t422","dur":"397","m":"[]","r":"[]","fam":"fam1","prio":"1"},
{"name":"t423","dur":"11","m":"[]","r":"[]","fam":"fam1","prio":"1"},
{"name":"t424","dur":"700","m":"[]","r":"[]","fam":"fam1","prio":"1"},
{"name":"t425","dur":"631","m":"[]","r":"[]","fam":"fam1","prio":"1"},
{"name":"t426","dur":"752","m":"[m5]","r":"[]","fam":"fam1","prio":"1"},
{"name":"t427","dur":"180","m":"[]","r":"[]","fam":"fam1","prio":"1"},
{"name":"t428","dur":"570","m":"[]","r":"[]","fam":"fam1","prio":"1"},
{"name":"t429","dur":"4","m":"[]","r":"[r3, r6, r10, r2, r1]","fam":"fam1","prio":"1"},
{"name":"t430","dur":"366","m":"[]","r":"[]","fam":"fam1","prio":"1"},
{"name":"t431","dur":"388","m":"[]","r":"[r8, r7, r4]","fam":"fam1","prio":"1"},
{"name":"t432","dur":"631","m":"[]","r":"[]","fam":"fam1","prio":"1"},
{"name":"t433","dur":"19","m":"[]","r":"[]","fam":"fam1","prio":"1"},
{"name":"t434","dur":"611","m":"[]","r":"[r7, r3, r5, r4, r6, r1, r8, r10, r2]","fam":"fam1","prio":"1"},
{"name":"t435","dur":"207","m":"[]","r":"[]","fam":"fam1","prio":"1"},
{"name":"t436","dur":"55","m":"[]","r":"[]","fam":"fam1","prio":"1"},
{"name":"t437","dur":"555","m":"[]","r":"[]","fam":"fam1","prio":"1"},
{"name":"t438","dur":"655","m":"[]","r":"[]","fam":"fam1","prio":"1"},
{"name":"t439","dur":"127","m":"[]","r":"[]","fam":"fam1","prio":"1"},
{"name":"t440","dur":"199","m":"[]","r":"[]","fam":"fam1","prio":"1"},
{"name":"t441","dur":"655","m":"[m3, m8, m1, m13]","r":"[]","fam":"fam1","prio":"1"},
{"name":"t442","dur":"283","m":"[]","r":"[]","fam":"fam1","prio":"1"},
{"name":"t443","dur":"149","m":"[m3, m20, m4, m9, m13, m17, m2]","r":"[]","fam":"fam1","prio":"1"},
{"name":"t444","dur":"730","m":"[]","r":"[]","fam":"fam1","prio":"1"},
{"name":"t445","dur":"284","m":"[m17, m4]","r":"[r2]","fam":"fam1","prio":"1"},
{"name":"t446","dur":"705","m":"[]","r":"[]","fam":"fam1","prio":"1"},
{"name":"t447","dur":"747","m":"[]","r":"[]","fam":"fam1","prio":"1"},
{"name":"t448","dur":"363","m":"[]","r":"[]","fam":"fam1","prio":"1"},
{"name":"t449","dur":"189","m":"[m15, m9]","r":"[r1, r3, r6, r9]","fam":"fam1","prio":"1"},
{"name":"t450","dur":"434","m":"[]","r":"[r5, r1, r9, r6, r2, r4, r8, r3, r10]","fam":"fam1","prio":"1"},
{"name":"t451","dur":"546","m":"[]","r":"[r9, r2]","fam":"fam1","prio":"1"},
{"name":"t452","dur":"548","m":"[]","r":"[r1, r10, r5]","fam":"fam1","prio":"1"},
{"name":"t453","dur":"291","m":"[]","r":"[]","fam":"fam1","prio":"1"},
{"name":"t454","dur":"444","m":"[m5, m17, m4, m9]","r":"[]","fam":"fam1","prio":"1"},
{"name":"t455","dur":"409","m":"[]","r":"[]","fam":"fam1","prio":"1"},
{"name":"t456","dur":"97","m":"[]","r":"[r1]","fam":"fam1","prio":"1"},
{"name":"t457","dur":"91","m":"[]","r":"[]","fam":"fam1","prio":"1"},
{"name":"t458","dur":"132","m":"[]","r":"[]","fam":"fam1","prio":"1"},
{"name":"t459","dur":"105","m":"[m16, m14]","r":"[]","fam":"fam1","prio":"1"},
{"name":"t460","dur":"151","m":"[]","r":"[]","fam":"fam1","prio":"1"},
{"name":"t461","dur":"461","m":"[]","r":"[r7, r9, r3, r8, r1, r10, r2, r6, r5, r4]","fam":"fam1","prio":"1"},
{"name":"t462","dur":"147","m":"[]","r":"[r7]","fam":"fam1","prio":"1"},
{"name":"t463","dur":"579","m":"[]","r":"[]","fam":"fam1","prio":"1"},
{"name":"t464","dur":"673","m":"[]","r":"[r4, r10, r8, r2, r1]","fam":"fam1","prio":"1"},
{"name":"t465","dur":"538","m":"[]","r":"[r1, r7, r6, r10, r3]","fam":"fam1","prio":"1"},
{"name":"t466","dur":"425","m":"[]","r":"[]","fam":"fam1","prio":"1"},
{"name":"t467","dur":"73","m":"[m12, m9, m7, m3]","r":"[]","fam":"fam1","prio":"1"},
{"name":"t468","dur":"293","m":"[]","r":"[]","fam":"fam1","prio":"1"},
{"name":"t469","dur":"225","m":"[]","r":"[]","fam":"fam1","prio":"1"},
{"name":"t470","dur":"219","m":"[]","r":"[]","fam":"fam1","prio":"1"},
{"name":"t471","dur":"271","m":"[m19, m13, m14]","r":"[r6, r9, r5, r7, r10, r2, r3, r4, r1, r8]","fam":"fam1","prio":"1"},
{"name":"t472","dur":"290","m":"[]","r":"[r1, r10, r6, r8, r4]","fam":"fam1","prio":"1"},
{"name":"t473","dur":"152","m":"[]","r":"[r5, r8, r9, r1]","fam":"fam1","prio":"1"},
{"name":"t474","dur":"250","m":"[]","r":"[r9, r4]","fam":"fam1","prio":"1"},
{"name":"t475","dur":"261","m":"[]","r":"[]","fam":"fam1","prio":"1"},
{"name":"t476","dur":"791","m":"[m11, m7, m19]","r":"[]","fam":"fam1","prio":"1"},
{"name":"t477","dur":"666","m":"[m15, m9, m10, m3, m17, m5, m20]","r":"[r4]","fam":"fam1","prio":"1"},
{"name":"t478","dur":"248","m":"[m8, m6, m14, m9, m5, m10]","r":"[r5, r6, r10, r3, r1, r9]","fam":"fam1","prio":"1"},
{"name":"t479","dur":"602","m":"[m8, m18, m4, m5, m19]","r":"[r10, r9, r5, r3, r1, r4, r7, r2, r8, r6]","fam":"fam1","prio":"1"},
{"name":"t480","dur":"759","m":"[]","r":"[]","fam":"fam1","prio":"1"},
{"name":"t481","dur":"704","m":"[m3, m8, m5, m12, m11, m16, m6]","r":"[]","fam":"fam1","prio":"1"},
{"name":"t482","dur":"390","m":"[]","r":"[]","fam":"fam1","prio":"1"},
{"name":"t483","dur":"390","m":"[]","r":"[r5, r1]","fam":"fam1","prio":"1"},
{"name":"t484","dur":"739","m":"[]","r":"[]","fam":"fam1","prio":"1"},
{"name":"t485","dur":"291","m":"[m1, m5, m11, m10]","r":"[]","fam":"fam1","prio":"1"},
{"name":"t486","dur":"576","m":"[m20, m17, m1, m18, m16, m8, m11, m10]","r":"[]","fam":"fam1","prio":"1"},
{"name":"t487","dur":"623","m":"[]","r":"[]","fam":"fam1","prio":"1"},
{"name":"t488","dur":"123","m":"[]","r":"[r8, r1, r7, r5, r6]","fam":"fam1","prio":"1"},
{"name":"t489","dur":"89","m":"[m6, m12, m4, m10, m16, m17, m18]","r":"[]","fam":"fam1","prio":"1"},
{"name":"t490","dur":"584","m":"[]","r":"[]","fam":"fam1","prio":"1"},
{"name":"t491","dur":"114","m":"[]","r":"[]","fam":"fam1","prio":"1"},
{"name":"t492","dur":"138","m":"[]","r":"[r6, r10, r9, r1, r8, r7, r4]","fam":"fam1","prio":"1"},
{"name":"t493","dur":"51","m":"[]","r":"[]","fam":"fam1","prio":"1"},
{"name":"t494","dur":"785","m":"[m6, m2, m7, m3]","r":"[r10, r5, r6]","fam":"fam1","prio":"1"},
{"name":"t495","dur":"588","m":"[m1]","r":"[]","fam":"fam1","prio":"1"},
{"name":"t496","dur":"590","m":"[]","r":"[]","fam":"fam1","prio":"1"},
{"name":"t497","dur":"239","m":"[]","r":"[]","fam":"fam1","prio":"1"},
{"name":"t498","dur":"213","m":"[]","r":"[r8, r10, r4, r9]","fam":"fam1","prio":"1"},
{"name":"t499","dur":"84","m":"[]","r":"[]","fam":"fam1","prio":"1"},
{"name":"t500","dur":"221","m":"[]","r":"[]","fam":"fam1","prio":"1"}],
"boards":[
"m1",
"m2",
"m3",
"m4",
"m5",
"m6",
"m7",
"m8",
"m9",
"m10",
"m11",
"m12",
"m13",
"m14",
"m15",
"m16",
"m17",
"m18",
"m19",
"m20"],
"resources":[
{"name":"r1","qty":1},
{"name":"r2","qty":1},
{"name":"r3","qty":1},
{"name":"r4","qty":1},
{"name":"r5","qty":1},
{"name":"r6","qty":1},
{"name":"r7","qty":1},
{"name":"r8","qty":1},
{"name":"r9","qty":1},
{"name":"r10","qty":1}],
"name":"t500m20r10-4.pl"
}
