{"test":[
{"name":"t1","dur":"103","m":"[]","r":"[]","fam":"fam1","prio":"1"},
{"name":"t2","dur":"135","m":"[]","r":"[]","fam":"fam1","prio":"1"},
{"name":"t3","dur":"138","m":"[]","r":"[]","fam":"fam1","prio":"1"},
{"name":"t4","dur":"266","m":"[]","r":"[]","fam":"fam1","prio":"1"},
{"name":"t5","dur":"308","m":"[]","r":"[r1]","fam":"fam1","prio":"1"},
{"name":"t6","dur":"2","m":"[]","r":"[]","fam":"fam1","prio":"1"},
{"name":"t7","dur":"228","m":"[]","r":"[r1, r3, r2]","fam":"fam1","prio":"1"},
{"name":"t8","dur":"190","m":"[]","r":"[]","fam":"fam1","prio":"1"},
{"name":"t9","dur":"678","m":"[m1, m12, m16, m2]","r":"[]","fam":"fam1","prio":"1"},
{"name":"t10","dur":"264","m":"[]","r":"[]","fam":"fam1","prio":"1"},
{"name":"t11","dur":"396","m":"[]","r":"[r3, r2]","fam":"fam1","prio":"1"},
{"name":"t12","dur":"632","m":"[]","r":"[]","fam":"fam1","prio":"1"},
{"name":"t13","dur":"187","m":"[]","r":"[]","fam":"fam1","prio":"1"},
{"name":"t14","dur":"4","m":"[]","r":"[]","fam":"fam1","prio":"1"},
{"name":"t15","dur":"585","m":"[]","r":"[]","fam":"fam1","prio":"1"},
{"name":"t16","dur":"502","m":"[]","r":"[]","fam":"fam1","prio":"1"},
{"name":"t17","dur":"186","m":"[]","r":"[]","fam":"fam1","prio":"1"},
{"name":"t18","dur":"215","m":"[m9]","r":"[r3, r1]","fam":"fam1","prio":"1"},
{"name":"t19","dur":"87","m":"[]","r":"[]","fam":"fam1","prio":"1"},
{"name":"t20","dur":"656","m":"[]","r":"[r2, r3]","fam":"fam1","prio":"1"},
{"name":"t21","dur":"523","m":"[]","r":"[]","fam":"fam1","prio":"1"},
{"name":"t22","dur":"66","m":"[]","r":"[]","fam":"fam1","prio":"1"},
{"name":"t23","dur":"252","m":"[]","r":"[r1, r3]","fam":"fam1","prio":"1"},
{"name":"t24","dur":"655","m":"[]","r":"[]","fam":"fam1","prio":"1"},
{"name":"t25","dur":"16","m":"[]","r":"[r2, r3]","fam":"fam1","prio":"1"},
{"name":"t26","dur":"170","m":"[]","r":"[]","fam":"fam1","prio":"1"},
{"name":"t27","dur":"293","m":"[]","r":"[]","fam":"fam1","prio":"1"},
{"name":"t28","dur":"477","m":"[]","r":"[r2, r1]","fam":"fam1","prio":"1"},
{"name":"t29","dur":"34","m":"[]","r":"[r3]","fam":"fam1","prio":"1"},
{"name":"t30","dur":"288","m":"[]","r":"[]","fam":"fam1","prio":"1"},
{"name":"t31","dur":"577","m":"[]","r":"[]","fam":"fam1","prio":"1"},
{"name":"t32","dur":"483","m":"[]","r":"[]","fam":"fam1","prio":"1"},
{"name":"t33","dur":"278","m":"[]","r":"[r1]","fam":"fam1","prio":"1"},
{"name":"t34","dur":"184","m":"[]","r":"[]","fam":"fam1","prio":"1"},
{"name":"t35","dur":"396","m":"[]","r":"[]","fam":"fam1","prio":"1"},
{"name":"t36","dur":"77","m":"[]","r":"[r2]","fam":"fam1","prio":"1"},
{"name":"t37","dur":"138","m":"[m12, m14]","r":"[r1, r2]","fam":"fam1","prio":"1"},
{"name":"t38","dur":"597","m":"[]","r":"[]","fam":"fam1","prio":"1"},
{"name":"t39","dur":"150","m":"[]","r":"[]","fam":"fam1","prio":"1"},
{"name":"t40","dur":"678","m":"[]","r":"[]","fam":"fam1","prio":"1"},
{"name":"t41","dur":"389","m":"[]","r":"[]","fam":"fam1","prio":"1"},
{"name":"t42","dur":"656","m":"[]","r":"[]","fam":"fam1","prio":"1"},
{"name":"t43","dur":"7","m":"[]","r":"[r3, r1, r2]","fam":"fam1","prio":"1"},
{"name":"t44","dur":"387","m":"[m9, m15, m3, m17, m6]","r":"[]","fam":"fam1","prio":"1"},
{"name":"t45","dur":"226","m":"[]","r":"[]","fam":"fam1","prio":"1"},
{"name":"t46","dur":"363","m":"[m20]","r":"[r3]","fam":"fam1","prio":"1"},
{"name":"t47","dur":"51","m":"[]","r":"[r3, r2, r1]","fam":"fam1","prio":"1"},
{"name":"t48","dur":"194","m":"[]","r":"[]","fam":"fam1","prio":"1"},
{"name":"t49","dur":"396","m":"[m5, m13, m8, m3, m20]","r":"[]","fam":"fam1","prio":"1"},
{"name":"t50","dur":"126","m":"[]","r":"[]","fam":"fam1","prio":"1"}],
"boards":[
"m1",
"m2",
"m3",
"m4",
"m5",
"m6",
"m7",
"m8",
"m9",
"m10",
"m11",
"m12",
"m13",
"m14",
"m15",
"m16",
"m17",
"m18",
"m19",
"m20"],
"resources":[
{"name":"r1","qty":1},
{"name":"r2","qty":1},
{"name":"r3","qty":1}],
"name":"t50m20r3-15.pl"
}
